{
  "ovfxVersion": "0.4.0",
  "id": "5c8d1e2a-3f4b-4a5c-9d8e-7f6a5b4c3d2e",
  "createdAt": "2026-04-15T11:30:00Z",
  "test": {
    "type": "static",
    "eye": "left",
    "extendedField": false,
    "pattern": "24-2",
    "strategy": "SITA-standard",
    "durationSeconds": 360,
    "stimulusDurationMs": 200,
    "interStimulusIntervalMs": 1500,
    "interStimulusIntervalJitterMs": 200
  },
  "calibration": {
    "setup": {
      "type": "screen",
      "screen": {
        "viewingDistanceCm": 50,
        "pixelsPerDegree": 12.0,
        "screenWidthPx": 1920,
        "screenHeightPx": 1080,
        "fixationOffsetPx": 384,
        "maxEccentricityDeg": 70,
        "brightnessFloor": 0.04,
        "maxLuminanceCdM2": 318.0,
        "backgroundLuminanceCdM2": 10.0
      }
    }
  },
  "stimuli": [
    { "key": "V4e",   "sizeDeg": 1.73, "intensity": 1.00, "luminanceCdM2": 318.0 },
    { "key": "III4e", "sizeDeg": 0.43, "intensity": 1.00, "luminanceCdM2": 318.0 },
    { "key": "III2e", "sizeDeg": 0.43, "intensity": 0.10, "luminanceCdM2": 31.8 },
    { "key": "I4e",   "sizeDeg": 0.11, "intensity": 1.00, "luminanceCdM2": 318.0 },
    { "key": "I2e",   "sizeDeg": 0.11, "intensity": 0.10, "luminanceCdM2": 31.8 }
  ],
  "points": [
    { "stimulusKey": "V4e", "meridianDeg": 15,  "eccentricityDeg": 65.0, "detected": true,  "responseTimeMs": 410, "sensitivityDb": 28 },
    { "stimulusKey": "V4e", "meridianDeg": 45,  "eccentricityDeg": 60.5, "detected": true,  "responseTimeMs": 380, "sensitivityDb": 30 },
    { "stimulusKey": "V4e", "meridianDeg": 75,  "eccentricityDeg": 50.0, "detected": true,  "responseTimeMs": 395, "sensitivityDb": 27 },
    { "stimulusKey": "V4e", "meridianDeg": 105, "eccentricityDeg": 55.5, "detected": true,  "responseTimeMs": 405 },
    { "stimulusKey": "V4e", "meridianDeg": 135, "eccentricityDeg": 62.0, "detected": true,  "responseTimeMs": 388 },
    { "stimulusKey": "V4e", "meridianDeg": 165, "eccentricityDeg": 64.0, "detected": true,  "responseTimeMs": 400 },
    { "stimulusKey": "V4e", "meridianDeg": 195, "eccentricityDeg": 60.0, "detected": true,  "responseTimeMs": 415 },
    { "stimulusKey": "V4e", "meridianDeg": 225, "eccentricityDeg": 58.0, "detected": true,  "responseTimeMs": 420 },
    { "stimulusKey": "V4e", "meridianDeg": 255, "eccentricityDeg": 50.0, "detected": true,  "responseTimeMs": 405 },
    { "stimulusKey": "V4e", "meridianDeg": 285, "eccentricityDeg": 55.0, "detected": true,  "responseTimeMs": 392 },
    { "stimulusKey": "V4e", "meridianDeg": 315, "eccentricityDeg": 60.5, "detected": true,  "responseTimeMs": 401 },
    { "stimulusKey": "V4e", "meridianDeg": 345, "eccentricityDeg": 64.5, "detected": true,  "responseTimeMs": 397 },

    { "stimulusKey": "III4e", "meridianDeg": 0,   "eccentricityDeg": 50.0, "detected": true,  "responseTimeMs": 432 },
    { "stimulusKey": "III4e", "meridianDeg": 90,  "eccentricityDeg": 38.0, "detected": true,  "responseTimeMs": 411 },
    { "stimulusKey": "III4e", "meridianDeg": 180, "eccentricityDeg": 45.0, "detected": true,  "responseTimeMs": 425 },
    { "stimulusKey": "III4e", "meridianDeg": 270, "eccentricityDeg": 42.0, "detected": true,  "responseTimeMs": 440 },
    { "stimulusKey": "III4e", "meridianDeg": 45,  "eccentricityDeg": 40.0, "detected": false },

    { "stimulusKey": "I2e",   "meridianDeg": 0,   "eccentricityDeg": 18.0, "detected": true,  "responseTimeMs": 510 },
    { "stimulusKey": "I2e",   "meridianDeg": 30,  "eccentricityDeg": 25.0, "detected": false },
    { "stimulusKey": "I2e",   "meridianDeg": 90,  "eccentricityDeg": 12.0, "detected": true,  "responseTimeMs": 488 },
    { "stimulusKey": "I2e",   "meridianDeg": 180, "eccentricityDeg": 16.0, "detected": true,  "responseTimeMs": 502 },
    { "stimulusKey": "I2e",   "meridianDeg": 270, "eccentricityDeg": 15.5, "detected": true,  "responseTimeMs": 495 },

    { "stimulusKey": "V4e",   "meridianDeg": 195, "eccentricityDeg": 14.5, "detected": false, "catchTrial": true },
    { "stimulusKey": "V4e",   "meridianDeg": 195, "eccentricityDeg": 14.5, "detected": false, "catchTrial": true },
    { "stimulusKey": "V4e",   "meridianDeg": 195, "eccentricityDeg": 14.5, "detected": false, "catchTrial": true },
    { "stimulusKey": "V4e",   "meridianDeg": 195, "eccentricityDeg": 14.5, "detected": false, "catchTrial": true },
    { "stimulusKey": "V4e",   "meridianDeg": 195, "eccentricityDeg": 14.5, "detected": false, "catchTrial": true },
    { "stimulusKey": "V4e",   "meridianDeg": 195, "eccentricityDeg": 14.5, "detected": false, "catchTrial": true },
    { "stimulusKey": "V4e",   "meridianDeg": 195, "eccentricityDeg": 14.5, "detected": false, "catchTrial": true },
    { "stimulusKey": "V4e",   "meridianDeg": 195, "eccentricityDeg": 14.5, "detected": false, "catchTrial": true },
    { "stimulusKey": "V4e",   "meridianDeg": 195, "eccentricityDeg": 14.5, "detected": false, "catchTrial": true },
    { "stimulusKey": "V4e",   "meridianDeg": 195, "eccentricityDeg": 14.5, "detected": true,  "catchTrial": true }
  ],
  "reliabilityIndices": {
    "catchTrialsPresented": 10,
    "catchTrialsFalsePositive": 1,
    "falsePositiveIsiPresses": 2,
    "truePositiveResponses": 87
  },
  "reliability": {
    "falsePositiveRate": 0.02,
    "falseNegativeRate": 0.05,
    "fixationLossRate": 0.08,
    "fixationMethod": "blind-spot"
  },
  "software": {
    "name": "Visual Field Check",
    "version": "1.0.0",
    "url": "https://visualfieldcheck.com"
  }
}
